{
  "main": {
    "id": "ddb80abeefcb9bf7",
    "type": "split",
    "children": [
      {
        "id": "61c4502ce1949481",
        "type": "tabs",
        "children": [
          {
            "id": "8dc9c9b08a2ab055",
            "type": "leaf",
            "state": {
              "type": "markdown",
              "state": {
                "file": "2023-12-29.md",
                "mode": "source",
                "source": false
              }
            }
          }
        ]
      }
    ],
    "direction": "vertical"
  },
  "left": {
    "id": "708430fda448950b",
    "type": "split",
    "children": [
      {
        "id": "3217ddeb158c1ad9",
        "type": "tabs",
        "children": [
          {
            "id": "34cf3210bf159c10",
            "type": "leaf",
            "state": {
              "type": "file-explorer",
              "state": {
                "sortOrder": "alphabetical"
              }
            }
          },
          {
            "id": "5b841cd4a4096527",
            "type": "leaf",
            "state": {
              "type": "search",
              "state": {
                "query": "git",
                "matchingCase": false,
                "explainSearch": false,
                "collapseAll": false,
                "extraContext": false,
                "sortOrder": "alphabetical"
              }
            }
          },
          {
            "id": "12bd1078ea8f4236",
            "type": "leaf",
            "state": {
              "type": "bookmarks",
              "state": {}
            }
          }
        ]
      }
    ],
    "direction": "horizontal",
    "width": 300
  },
  "right": {
    "id": "2291b604d11cb157",
    "type": "split",
    "children": [
      {
        "id": "3c18f862f8bb88e9",
        "type": "tabs",
        "children": [
          {
            "id": "cbc38b59b335f02b",
            "type": "leaf",
            "state": {
              "type": "backlink",
              "state": {
                "file": "2023-12-29.md",
                "collapseAll": false,
                "extraContext": false,
                "sortOrder": "alphabetical",
                "showSearch": false,
                "searchQuery": "",
                "backlinkCollapsed": false,
                "unlinkedCollapsed": true
              }
            }
          },
          {
            "id": "a870df5479b4348a",
            "type": "leaf",
            "state": {
              "type": "outgoing-link",
              "state": {
                "file": "2023-12-29.md",
                "linksCollapsed": false,
                "unlinkedCollapsed": true
              }
            }
          },
          {
            "id": "c535e0a368ce6a3f",
            "type": "leaf",
            "state": {
              "type": "tag",
              "state": {
                "sortOrder": "frequency",
                "useHierarchy": true
              }
            }
          },
          {
            "id": "501c699bc3b27487",
            "type": "leaf",
            "state": {
              "type": "outline",
              "state": {
                "file": "2023-12-29.md"
              }
            }
          },
          {
            "id": "177150abc06e1656",
            "type": "leaf",
            "state": {
              "type": "reminder-list",
              "state": {}
            }
          },
          {
            "id": "858bf5a7f837698f",
            "type": "leaf",
            "state": {
              "type": "FANTASY_CALENDAR",
              "state": {}
            }
          }
        ],
        "currentTab": 5
      }
    ],
    "direction": "horizontal",
    "width": 543.5
  },
  "left-ribbon": {
    "hiddenItems": {
      "switcher:打开快速切换": false,
      "graph:查看关系图谱": false,
      "canvas:新建白板": false,
      "daily-notes:打开/创建今天的日记": false,
      "templates:插入模板": false,
      "command-palette:打开命令面板": false,
      "obsidian-full-calendar:Open Full Calendar": false,
      "obsidian-day-planner:Timeline": false,
      "fantasy-calendar:Open Large Fantasy Calendar": false
    }
  },
  "active": "8dc9c9b08a2ab055",
  "lastOpenFiles": [
    "2023-12-28.md",
    "2023-12-29.md",
    "400Calendar/2024-01-02 发布校园卡充值通知.md",
    "400Calendar/2024-01-09 值班，提前做好准备.md",
    "400Calendar",
    "000Git学习笔记/000.Git从入门到精通，Git命令大全（目录）.md",
    "000Git学习笔记/033.获取远端仓库代码.md",
    "Accessories",
    "files",
    "新建文件夹",
    "obsidian学习笔记",
    "Git学习笔记/045.重命名分支 git branch -M.md",
    "Git学习笔记/045.分支列表 git branch.md",
    "000.Git从入门到精通，Git命令大全（目录）.md",
    "Git学习笔记/044.删除分支 git branch -d.md",
    "Git学习笔记/043.合并分支命令 git merge.md",
    "Git学习笔记/042.切换分支命令 git checkout.md",
    "Git学习笔记/041.创建分支命令 git branch.md",
    "Git学习笔记/040.Git 分支.md",
    "Git学习笔记/035.推送 git push.md",
    "Git学习笔记/034.拉取 git pull.md",
    "Git学习笔记/033.获取远端仓库代码 git fetch.md",
    "Git学习笔记/032.查看远端仓库.md",
    "Git学习笔记/031.添加远程仓库.md",
    "Git学习笔记/030 .Git远程仓库.md",
    "Git学习笔记/022. .git目录.md",
    "Git学习笔记/021. .gitignore.md",
    "Git学习笔记/020Git项目文件说明.md",
    "Git学习笔记/014.git重命名检测.md",
    "Git学习笔记/013.HEAD是什么.md",
    "Git学习笔记/012.Git文件状态.md",
    "Git学习笔记",
    "GitStudying",
    "gti学习过程.txt",
    "Pasted image 20231228092749.png",
    "Pasted image 20231228090425.png"
  ]
}